[
  {
    "title": "cat",
    "image": "cat.gif",
    "link": "https://%E7%8C%AB.%E7%A7%BB%E5%8A%A8"
  },
  {
    "title": "agoraroad",
    "image": "agoraroad.gif",
    "link": "https://forum.agoraroad.com/index.php"
  },
    {
    "title": "3to",
    "image": "3to.gif",
    "link": "https://3to.moe"
  },
  {
    "title": "galladite",
    "image": "galladite.gif",
    "link": "https://galladite.net/~galladite/"
  },
  {
    "title": "heimdall",
    "image": "heimdall.gif",
    "link": "https://heimdall.pm"
  },
  {
    "title": "korosama",
    "image": "korosama.gif",
    "link": "https://korosama.neocities.org"
  },
  {
    "title": "newdigitalera",
    "image": "newdigitalera.png",
    "link": "https://newdigitalera.neocities.org"
  },
  {
    "title": "ophanim",
    "image": "ophanim.gif",
    "link": "https://ophanim.neocities.org"
  },
  {
    "title": "yukinu",
    "image": "yukinu.gif",
    "link": "https://yukinu.com"
  },
  {
    "title": "sketch",
    "image": "sketch.png",
    "link": "https://twitter.com/sketchygfx__"
  },
  {
    "title": "foreverliketh.is",
    "image": "foreverliketh.is.gif",
    "link": "https://foreverliketh.is/"
  },
  {
    "title": "crystal.tilde.institute",
    "image": "crystal-tilde.gif",
    "link": "https://crystal.tilde.institute/"
  },
  {
    "title": "the_arcade",
    "image": "the_arcade.gif",
    "link": "https://articexploit.xyz/"
  },
  {
    "title": "grafo.zone",
    "image": "grafo.gif",
    "link": "https://grafo.zone/"
  }
]
